camminapy/__init__.py
camminapy/data/__init__.py
camminapy/data/resample.py
camminapy/plot/__init__.py
camminapy/plot/altair_config.py
camminapy/plot/altair_theme.py
camminapy/plot/footer.py
camminapy/utils/__init__.py
camminapy/utils/config.py
camminapy/utils/logger.py
camminapy-1.1.11.dist-info/LICENSE
camminapy-1.1.11.dist-info/METADATA
camminapy-1.1.11.dist-info/WHEEL
camminapy-1.1.11.dist-info/RECORD
